{"files":{"new.html":{"frameworks":["wordpress.pinegrow","bs3.3.4","html"]},"index.html":{"frameworks":["wordpress.pinegrow","fontawesome","bs3.3.4","html"]},"single.html":{"frameworks":["wordpress.pinegrow","fontawesome","bs3.3.4","html"]},"page.html":{"frameworks":["wordpress.pinegrow","fontawesome","bs3.3.4","html"]},"archive.html":{"frameworks":["wordpress.pinegrow","fontawesome","bs3.3.4","html"]},"search.html":{"frameworks":["wordpress.pinegrow","fontawesome","bs3.3.4","html"]},"404.html":{"frameworks":["wordpress.pinegrow","fontawesome","bs3.3.4","html"]}},"breakpoints":[480,768,992,1200]}